MANIFEST.in
setup.cfg
setup.py
seishub/__init__.py
seishub.core.egg-info/PKG-INFO
seishub.core.egg-info/SOURCES.txt
seishub.core.egg-info/dependency_links.txt
seishub.core.egg-info/entry_points.txt
seishub.core.egg-info/namespace_packages.txt
seishub.core.egg-info/not-zip-safe
seishub.core.egg-info/requires.txt
seishub.core.egg-info/top_level.txt
seishub/core/LICENSE.txt
seishub/core/README.txt
seishub/core/VERSION.txt
seishub/core/__init__.py
seishub/core/auth.py
seishub/core/config.py
seishub/core/core.py
seishub/core/daemon.py
seishub/core/defaults.py
seishub/core/env.py
seishub/core/exceptions.py
seishub/core/log.py
seishub/core/test.py
seishub/core/db/__init__.py
seishub/core/db/manager.py
seishub/core/db/orm.py
seishub/core/db/util.py
seishub/core/db/tests/__init__.py
seishub/core/db/tests/test_orm.py
seishub/core/db/tests/test_util.py
seishub/core/packages/__init__.py
seishub/core/packages/builtins.py
seishub/core/packages/installer.py
seishub/core/packages/interfaces.py
seishub/core/packages/admin/__init__.py
seishub/core/packages/admin/ssh/__init__.py
seishub/core/packages/admin/ssh/general.py
seishub/core/packages/admin/web/__init__.py
seishub/core/packages/admin/web/catalog.py
seishub/core/packages/admin/web/components.py
seishub/core/packages/admin/web/general.py
seishub/core/packages/admin/web/themes.py
seishub/core/packages/admin/web/statics/favicon.ico
seishub/core/packages/admin/web/statics/welcome.html
seishub/core/packages/admin/web/statics/css/magic.css
seishub/core/packages/admin/web/statics/css/oldstyle.css
seishub/core/packages/admin/web/statics/images/bg.png
seishub/core/packages/admin/web/statics/images/seishub.png
seishub/core/packages/admin/web/statics/js/default.js
seishub/core/packages/admin/web/statics/yui2/assets/accordion.css
seishub/core/packages/admin/web/statics/yui2/assets/accordion.js
seishub/core/packages/admin/web/statics/yui2/assets/calbtn.gif
seishub/core/packages/admin/web/statics/yui2/assets/treeview-loading.gif
seishub/core/packages/admin/web/statics/yui2/assets/treeview-menu.css
seishub/core/packages/admin/web/statics/yui2/assets/treeview-menu.gif
seishub/core/packages/admin/web/statics/yui2/assets/treeview-sprite.css
seishub/core/packages/admin/web/statics/yui2/assets/treeview-sprite.png
